ztf_plan_obs/__init__.py
ztf_plan_obs/api.py
ztf_plan_obs/credentials.py
ztf_plan_obs/fritzconnector.py
ztf_plan_obs/gcn_parser.py
ztf_plan_obs/multiday_plan.py
ztf_plan_obs/plan.py
ztf_plan_obs/utils.py
ztf_plan_obs-0.34.dist-info/LICENSE
ztf_plan_obs-0.34.dist-info/METADATA
ztf_plan_obs-0.34.dist-info/WHEEL
ztf_plan_obs-0.34.dist-info/top_level.txt
ztf_plan_obs-0.34.dist-info/RECORD
