Metadata-Version: 2.1
Name: ztf-plan-obs
Version: 0.34
Summary: Plan observations with the Zwicky Transient Facility
Home-page: https://github.com/simeonreusch/ztf_plan_obs/
Download-URL: https://github.com/simeonreusch/ztf_plan_obs/archive/v0.34.tar.gz
Author: Simeon Reusch
Author-email: simeon.reusch@desy.de
Maintainer: Simeon Reusch
Maintainer-email: simeon.reusch@desy.de
License: BSD (3-clause)
Classifier: Intended Audience :: Science/Research
Classifier: Programming Language :: Python :: 3.8
Classifier: License :: OSI Approved :: BSD License
Classifier: Topic :: Scientific/Engineering :: Astronomy
Classifier: Operating System :: POSIX
Classifier: Operating System :: Unix
Classifier: Operating System :: MacOS
License-File: LICENSE
Requires-Dist: astropy
Requires-Dist: astroquery
Requires-Dist: coveralls
Requires-Dist: numpy
Requires-Dist: astroplan (>=0.7)
Requires-Dist: pandas
Requires-Dist: penquins
Requires-Dist: matplotlib
Requires-Dist: flask
Requires-Dist: ztfquery (>=1.15.7)
Requires-Dist: lxml
Requires-Dist: html5lib
Requires-Dist: shapely
Requires-Dist: geopandas
